CHANGES.rst
MANIFEST.in
README.rst
TODO.rst
bootstrap.sh
setup.cfg
setup.py
tox.ini
bin/crawl
bin/extract
bin/match
docs/Makefile
docs/check_docs.py
docs/make.bat
docs/requirements.txt
docs/build/doctrees/changes.doctree
docs/build/doctrees/environment.pickle
docs/build/doctrees/index.doctree
docs/build/doctrees/roadmap.doctree
docs/build/doctrees/todo.doctree
docs/build/doctrees/api/index.doctree
docs/build/doctrees/api/spyda.doctree
docs/build/html/.buildinfo
docs/build/html/changes.html
docs/build/html/genindex.html
docs/build/html/index.html
docs/build/html/objects.inv
docs/build/html/py-modindex.html
docs/build/html/roadmap.html
docs/build/html/search.html
docs/build/html/searchindex.js
docs/build/html/todo.html
docs/build/html/_sources/changes.txt
docs/build/html/_sources/index.txt
docs/build/html/_sources/roadmap.txt
docs/build/html/_sources/todo.txt
docs/build/html/_sources/api/index.txt
docs/build/html/_sources/api/spyda.txt
docs/build/html/_static/ajax-loader.gif
docs/build/html/_static/basic.css
docs/build/html/_static/comment-bright.png
docs/build/html/_static/comment-close.png
docs/build/html/_static/comment.png
docs/build/html/_static/default.css
docs/build/html/_static/doctools.js
docs/build/html/_static/down-pressed.png
docs/build/html/_static/down.png
docs/build/html/_static/file.png
docs/build/html/_static/jquery.js
docs/build/html/_static/minus.png
docs/build/html/_static/plus.png
docs/build/html/_static/pygments.css
docs/build/html/_static/rtd.css
docs/build/html/_static/searchtools.js
docs/build/html/_static/sidebar.js
docs/build/html/_static/underscore.js
docs/build/html/_static/up-pressed.png
docs/build/html/_static/up.png
docs/build/html/_static/websupport.js
docs/build/html/api/index.html
docs/build/html/api/spyda.html
docs/source/changes.rst
docs/source/conf.py
docs/source/index.rst
docs/source/roadmap.rst
docs/source/todo.rst
docs/source/_static/rtd.css
docs/source/_templates/layout.html
docs/source/api/index.rst
docs/source/api/spyda.rst
spyda.egg-info/PKG-INFO
spyda.egg-info/SOURCES.txt
spyda.egg-info/dependency_links.txt
spyda.egg-info/entry_points.txt
spyda.egg-info/requires.txt
spyda.egg-info/top_level.txt
spyda.egg-info/zip-safe
