Metadata-Version: 1.1
Name: spyda
Version: 0.0.2
Summary: Spyda - Python Spider Tool and Library
Home-page: https://bitbucket.org/prologic/spyda
Author: James Mills
Author-email: James Mills, j dot mills at griffith dot edu dot au
License: MIT
Download-URL: https://bitbucket.org/prologic/spyda/downloads/
Keywords: Python Spider Web Crawling and Extraction Tool and Library
Platform: POSIX
Classifier: Development Status :: 4 - Beta
Classifier: Environment :: Console
Classifier: Intended Audience :: Developers
Classifier: License :: OSI Approved :: MIT License
Classifier: Natural Language :: English
Classifier: Operating System :: MacOS :: MacOS X
Classifier: Operating System :: POSIX :: Linux
Classifier: Programming Language :: Python :: 2.7
Classifier: Topic :: Internet :: WWW/HTTP :: Indexing/Search
